magento_encryptor/__init__.py
magento_encryptor-0.2.dist-info/LICENSE
magento_encryptor-0.2.dist-info/METADATA
magento_encryptor-0.2.dist-info/WHEEL
magento_encryptor-0.2.dist-info/top_level.txt
magento_encryptor-0.2.dist-info/RECORD
