Metadata-Version: 2.1
Name: magento-encryptor
Version: 0.2
Summary: UNKNOWN
Home-page: https://github.com/flared/magento-encryptor-py
Author: Israël Hallé
Author-email: israel.halle@flare.systems
License: License :: OSI Approved :: GNU Lesser General Public License v3 (LGPLv3)
Platform: UNKNOWN
Requires-Python: >=3.5
Requires-Dist: PyNaCl (==1.4.0)
